SaisiZaoqike1to4/Dockerfile
SaisiZaoqike1to4/README.md
SaisiZaoqike1to4/__init__.py
SaisiZaoqike1to4/__main__.py
SaisiZaoqike1to4/file.epub
SaisiZaoqike1to4/index.html
SaisiZaoqike1to4/css/__init__.py
SaisiZaoqike1to4/css/annotations.css
SaisiZaoqike1to4/css/main.css
SaisiZaoqike1to4/css/normalize.css
SaisiZaoqike1to4/css/popup.css
SaisiZaoqike1to4/font/__init__.py
SaisiZaoqike1to4/font/fontello.eot
SaisiZaoqike1to4/font/fontello.svg
SaisiZaoqike1to4/font/fontello.ttf
SaisiZaoqike1to4/font/fontello.woff
SaisiZaoqike1to4/img/__init__.py
SaisiZaoqike1to4/img/annotator-glyph-sprite.png
SaisiZaoqike1to4/img/annotator-icon-sprite.png
SaisiZaoqike1to4/img/apple-touch-icon.png
SaisiZaoqike1to4/img/cancelfullscreen.png
SaisiZaoqike1to4/img/close.png
SaisiZaoqike1to4/img/fullscreen.png
SaisiZaoqike1to4/img/loader.gif
SaisiZaoqike1to4/img/menu-icon.png
SaisiZaoqike1to4/img/save.png
SaisiZaoqike1to4/img/saved.png
SaisiZaoqike1to4/img/settings-s.png
SaisiZaoqike1to4/img/settings.png
SaisiZaoqike1to4/img/star.png
SaisiZaoqike1to4/js/__init__.py
SaisiZaoqike1to4/js/epub.js
SaisiZaoqike1to4/js/epub.min.js
SaisiZaoqike1to4/js/epub.min.map
SaisiZaoqike1to4/js/hooks.min.js
SaisiZaoqike1to4/js/hooks.min.map
SaisiZaoqike1to4/js/reader.js
SaisiZaoqike1to4/js/reader.js.map
SaisiZaoqike1to4/js/reader.min.js
SaisiZaoqike1to4/js/reader.min.map
SaisiZaoqike1to4/js/hooks/__init__.py
SaisiZaoqike1to4/js/hooks/extensions/__init__.py
SaisiZaoqike1to4/js/hooks/extensions/highlight.js
SaisiZaoqike1to4/js/libs/__init__.py
SaisiZaoqike1to4/js/libs/jquery.min.js
SaisiZaoqike1to4/js/libs/localforage.min.js
SaisiZaoqike1to4/js/libs/screenfull.js
SaisiZaoqike1to4/js/libs/screenfull.min.js
SaisiZaoqike1to4/js/libs/zip.min.js
SaisiZaoqike1to4/js/plugins/__init__.py
SaisiZaoqike1to4/js/plugins/hypothesis.js
SaisiZaoqike1to4/js/plugins/search.js
saisi_zaoqike_1to4-2022.10.9.1.dist-info/METADATA
saisi_zaoqike_1to4-2022.10.9.1.dist-info/WHEEL
saisi_zaoqike_1to4-2022.10.9.1.dist-info/entry_points.txt
saisi_zaoqike_1to4-2022.10.9.1.dist-info/top_level.txt
saisi_zaoqike_1to4-2022.10.9.1.dist-info/RECORD
